[
  {
    "zeit": "2025-04-05T11:54:13.996346",
    "text": "\ud83d\udfe9 Positive News erkannt"
  },
  {
    "zeit": "2025-04-05T11:54:13.997232",
    "text": "\u26aa\ufe0f Kein klares Signal \u2013 Trend=NEUTRAL, Vola=0.3396, Conf=0.6"
  },
  {
    "zeit": "2025-04-05T11:57:22.327289",
    "text": "\ud83d\udfe9 Positive News erkannt"
  },
  {
    "zeit": "2025-04-05T11:57:22.328138",
    "text": "\u26aa\ufe0f Kein klares Signal \u2013 Trend=NEUTRAL, Vola=0.3413, Conf=0.4"
  },
  {
    "zeit": "2025-04-05T11:57:40.449900",
    "text": "\ud83d\udfe9 Positive News erkannt"
  },
  {
    "zeit": "2025-04-05T11:57:40.450271",
    "text": "\u26aa\ufe0f Kein klares Signal \u2013 Trend=NEUTRAL, Vola=0.3367, Conf=0.4"
  },
  {
    "zeit": "2025-04-05T12:02:05.654519",
    "text": "\ud83d\udfe9 Positive News erkannt"
  },
  {
    "zeit": "2025-04-05T12:02:05.655467",
    "text": "\u26aa\ufe0f Kein klares Signal \u2013 Trend=DOWN, Vola=0.3141, Conf=0.4"
  },
  {
    "zeit": "2025-04-05T12:02:24.048531",
    "text": "\ud83d\udfe9 Positive News erkannt"
  },
  {
    "zeit": "2025-04-05T12:02:24.048982",
    "text": "\u26aa\ufe0f Kein klares Signal \u2013 Trend=DOWN, Vola=0.3107, Conf=0.4"
  },
  {
    "zeit": "2025-04-05T12:02:42.207959",
    "text": "\ud83d\udfe9 Positive News erkannt"
  },
  {
    "zeit": "2025-04-05T12:02:42.208598",
    "text": "\u26aa\ufe0f Kein klares Signal \u2013 Trend=NEUTRAL, Vola=0.3124, Conf=0.4"
  },
  {
    "zeit": "2025-04-05T12:03:00.582220",
    "text": "\ud83d\udfe9 Positive News erkannt"
  },
  {
    "zeit": "2025-04-05T12:03:00.582771",
    "text": "\u26aa\ufe0f Kein klares Signal \u2013 Trend=NEUTRAL, Vola=0.3116, Conf=0.4"
  }
]